README.md
torch_logger/__init__.py
torch_logger/best_value_logger.py
torch_logger-0.1.1.dist-info/WHEEL
torch_logger-0.1.1.dist-info/METADATA
torch_logger-0.1.1.dist-info/RECORD
