Metadata-Version: 2.1
Name: torch-logger
Version: 0.1.1
Summary: A minimalist package for logging best values of metrics when training models with PyTorch
License: BSD-3-Clause
Author: Michael Moor
Requires-Python: >=3.8,<4.0
Classifier: License :: OSI Approved :: BSD License
Classifier: Programming Language :: Python :: 3
Classifier: Programming Language :: Python :: 3.10
Classifier: Programming Language :: Python :: 3.8
Classifier: Programming Language :: Python :: 3.9
